PyMysqlTools/__init__.py
PyMysqlTools/actuator.py
PyMysqlTools/exceptions.py
PyMysqlTools/generator.py
PyMysqlTools/main.py
PyMysqlTools/result_set.py
PyMysqlTools/settings.py
PyMysqlTools/test.py
PyMysqlTools-0.6.7.dist-info/LICENSE
PyMysqlTools-0.6.7.dist-info/METADATA
PyMysqlTools-0.6.7.dist-info/WHEEL
PyMysqlTools-0.6.7.dist-info/top_level.txt
PyMysqlTools-0.6.7.dist-info/RECORD
