Metadata-Version: 2.1
Name: PyMysqlTools
Version: 0.6.7
Summary: A library that makes MySQL operation more convenient.
Home-page: https://gitee.com/uraurara/PyMysqlTools
Author: ulala
Author-email: 2713389652@qq.com
License: MIT
Keywords: mysql,client,mysqluitls,PyMysqlTools
Platform: UNKNOWN
Classifier: Intended Audience :: Developers
Classifier: License :: OSI Approved :: MIT License
Classifier: Natural Language :: Chinese (Simplified)
Classifier: Programming Language :: Python :: 3.8
Requires-Python: >=3.8.10
License-File: LICENSE
Requires-Dist: setuptools ~=58.3.0
Requires-Dist: PyMySQL ~=1.0.2
Requires-Dist: DBUtils ~=3.0.2
